pyvivint/__init__.py
pyvivint/constants.py
pyvivint/entity.py
pyvivint/enums.py
pyvivint/exceptions.py
pyvivint/pubnub.py
pyvivint/system.py
pyvivint/utils.py
pyvivint/vivint.py
pyvivint/vivintskyapi.py
pyvivint/devices/__init__.py
pyvivint/devices/alarm_panel.py
pyvivint/devices/camera.py
pyvivint/devices/door_lock.py
pyvivint/devices/garage_door.py
pyvivint/devices/wireless_sensor.py
pyvivint-2021.1.1.dist-info/LICENSE
pyvivint-2021.1.1.dist-info/METADATA
pyvivint-2021.1.1.dist-info/WHEEL
pyvivint-2021.1.1.dist-info/top_level.txt
pyvivint-2021.1.1.dist-info/RECORD
