Metadata-Version: 2.1
Name: pyvivint
Version: 2021.1.1
Summary: Python module to interact with VivintSky API.
Home-page: https://github.com/ovirs/pyvivint
Author: Ovidiu Stateina, Nathan Spencer
Author-email: ovidiurs@gmail.com
License: MIT
Platform: UNKNOWN
Classifier: Programming Language :: Python :: 3
Classifier: License :: OSI Approved :: MIT License
Classifier: Operating System :: OS Independent
Classifier: Topic :: Home Automation
Requires-Dist: aiohttp (>=3.6)
Requires-Dist: certifi (>=2019.9.11)
